<?xml version = '1.0' encoding = 'UTF-8'?>
<Relation class="oracle.dbtools.crest.model.design.logical.Relation" name="Relation_3" directorySegmentName="seg_0" id="084E04CB-0798-3159-9092-A174B1D37C0B">
<createdBy>Saber</createdBy>
<createdTime>2024-09-17 16:34:54 UTC</createdTime>
<ownerDesignName>Modelo Base de datos</ownerDesignName>
<engineerTo>
<item key="E85DCC45-BBFC-C016-5034-8D5D598CBE39" value="true"/>
</engineerTo>
<identifying>false</identifying>
<optionalSource>true</optionalSource>
<optionalTarget>false</optionalTarget>
<sourceCardinality>*</sourceCardinality>
<sourceEntity>2F2AB6C6-10CE-6C4B-AFB2-09E4828C6369</sourceEntity>
<targetCardinalityString>1</targetCardinalityString>
<targetEntity>B58F35D2-FA4F-132D-991F-BFD3EE5E0F34</targetEntity>
<transferable>true</transferable>
<deleteRule>NO ACTION</deleteRule>
</Relation>